meta_self_learner-0.0.3.data/scripts/meta_self_learner_package
msl/MetaLearning.py
msl/cf_matrix.py
meta_self_learner-0.0.3.dist-info/METADATA
meta_self_learner-0.0.3.dist-info/WHEEL
meta_self_learner-0.0.3.dist-info/top_level.txt
meta_self_learner-0.0.3.dist-info/RECORD
