Metadata-Version: 2.1
Name: meta-self-learner
Version: 0.0.3
Summary: Meta Ensemble Self-Learning with Optimization Objective Functions
Home-page: https://github.com/ajayarunachalam/meta-self-learner/
Author: Ajay Arunachalam
Author-email: ajay.arunachalam08@gmail.com
License: UNKNOWN
Platform: UNKNOWN
Classifier: Programming Language :: Python :: 3
Classifier: License :: OSI Approved :: MIT License
Classifier: Operating System :: OS Independent
Requires-Dist: pandas
Requires-Dist: numpy
Requires-Dist: tabulate
Requires-Dist: xgboost
Requires-Dist: scipy
Requires-Dist: six
Requires-Dist: scikit-learn
Requires-Dist: matplotlib
Requires-Dist: plot-metric
